bnetprofile/__init__.py
bnetprofile/app.py
bnetprofile-0.0.1.dist-info/METADATA
bnetprofile-0.0.1.dist-info/RECORD
bnetprofile-0.0.1.dist-info/WHEEL
bnetprofile-0.0.1.dist-info/top_level.txt
