Metadata-Version: 2.1
Name: bnetprofile
Version: 0.0.1
Summary: SC2 Battle.net profile redirection app for All Inspiration Apps
Home-page: https://github.com/frugs/allin-bnetprofile
Author: Hugo Wainwright
Author-email: wainwrighthugo@gmail.com
License: UNKNOWN
Keywords: sc2,all-inspiration
Platform: UNKNOWN
Requires-Dist: requests (>=2.19.1)
Requires-Dist: requests-toolbelt (>=0.8.0)
Requires-Dist: Flask-OAuthlib
Requires-Dist: flask
Requires-Dist: google-cloud-datastore
